dnd_auction_game/__init__.py
dnd_auction_game/auction_house.py
dnd_auction_game/client.py
dnd_auction_game/connection_manager.py
dnd_auction_game/leadboard.py
dnd_auction_game/play.py
dnd_auction_game/server.py
dnd_auction_game-0.3.3.dist-info/licenses/LICENSE
dnd_auction_game-0.3.3.dist-info/METADATA
dnd_auction_game-0.3.3.dist-info/WHEEL
dnd_auction_game-0.3.3.dist-info/top_level.txt
dnd_auction_game-0.3.3.dist-info/RECORD
