Metadata-Version: 2.4
Name: dnd_auction_game
Version: 0.3.3
Summary: An auction game for trading-bots based on d&d die rolls.
Home-page: https://github.com/ooki/dnd_auction_game
Author: Sondre 'Ooki' Glimsdal
Author-email: sondre.glimsdal@gmail.com
License: MIT
Project-URL: Bug Tracker, https://github.com/ooki/dnd_auction_game/issues
Project-URL: Documentation, https://github.com/ooki/dnd_auction_game
Project-URL: Source Code, https://github.com/ooki/dnd_auction_game
Classifier: Development Status :: 4 - Beta
Classifier: Intended Audience :: Science/Research
Classifier: Intended Audience :: Developers
Classifier: License :: OSI Approved :: MIT License
Classifier: Programming Language :: Python
Classifier: Topic :: Scientific/Engineering
Classifier: Operating System :: Microsoft :: Windows
Classifier: Operating System :: POSIX
Classifier: Operating System :: Unix
Classifier: Operating System :: MacOS
Classifier: Programming Language :: Python :: 3 :: Only
Classifier: Programming Language :: Python :: 3
Classifier: Programming Language :: Python :: 3.9
Requires-Python: >=3.8
License-File: LICENSE
Requires-Dist: py-machineid>=0.4.5
Requires-Dist: fastapi
Requires-Dist: uvicorn
Requires-Dist: websockets
Requires-Dist: Jinja2
Dynamic: author
Dynamic: author-email
Dynamic: classifier
Dynamic: description
Dynamic: description-content-type
Dynamic: home-page
Dynamic: license
Dynamic: license-file
Dynamic: project-url
Dynamic: requires-dist
Dynamic: requires-python
Dynamic: summary
